dispono/__init__.py
dispono/dispono.py
dispono/static/coding_game.js
dispono/static/img/logo.svg
Dispono-0.1.0.dist-info/LICENSE
Dispono-0.1.0.dist-info/METADATA
Dispono-0.1.0.dist-info/WHEEL
Dispono-0.1.0.dist-info/top_level.txt
Dispono-0.1.0.dist-info/RECORD
