Metadata-Version: 2.1
Name: Dispono
Version: 0.1.0
Summary: Dispono is a synchronization program between your browser IDE and your local machine.
Home-page: https://github.com/Viatorus/seejeepee
Author: Toni Neubert
Author-email: lutztonineubert@gmail.com
License: MIT
Platform: UNKNOWN
Classifier: Development Status :: 4 - Beta
Classifier: Topic :: Software Development :: Build Tools
Classifier: License :: OSI Approved :: MIT License
Classifier: Programming Language :: Python
Classifier: Programming Language :: Python :: 3.6
Requires-Dist: aiohttp
Requires-Dist: aiohttp-cors
Requires-Dist: python-socketio
